MANIFEST.in
README.md
setup.py
pykush/__init__.py
pykush/pykush.py
pykush/pykush_bin.py
pykush.egg-info/PKG-INFO
pykush.egg-info/SOURCES.txt
pykush.egg-info/dependency_links.txt
pykush.egg-info/entry_points.txt
pykush.egg-info/requires.txt
pykush.egg-info/top_level.txt