Metadata-Version: 1.1
Name: pykush
Version: 0.0.2
Summary: Python interface for the Yepkit Switchable USB Hub
Home-page: https://github.com/alvarop/pykush
Author: Alvaro Prieto
Author-email: pykush@alvaroprieto.com
License: BSD License
Keywords: hardware firmware i2c spi gpio
Platform: UNKNOWN
Classifier: Development Status :: 3 - Alpha
Classifier: Intended Audience :: Developers
Classifier: Intended Audience :: Science/Research
Classifier: Intended Audience :: Education
Classifier: Topic :: Scientific/Engineering
Classifier: License :: OSI Approved :: BSD License
Classifier: Programming Language :: Python :: 2.7
